LICENSE
MANIFEST.in
README.rst
pyproject.toml
setup.cfg
setup.py
SALTISE_components.egg-info/PKG-INFO
SALTISE_components.egg-info/SOURCES.txt
SALTISE_components.egg-info/dependency_links.txt
SALTISE_components.egg-info/requires.txt
SALTISE_components.egg-info/top_level.txt
components/__init__.py
components/apps.py
components/static/components/img/avatar.jpg
components/static/components/img/collection-placeholder.svg
components/static/components/img/logo.gif
components/static/components/img/logo.png
components/static/components/img/logo.svg
components/static/components/img/vector-search.svg
components/static/components/js/build/createAssignment.min.js
components/static/components/js/build/createQuestion.min.js
components/static/components/js/build/createQuestions1.min.js
components/static/components/js/build/createQuestions2.min.js
components/static/components/js/build/dashboard.min.js
components/static/components/js/build/dashboardInvitedUser.min.js
components/static/components/js/build/dashboardNewUser.min.js
components/static/components/js/build/dashboardStudent.min.js
components/static/components/js/build/detailedAssignment.min.js
components/static/components/js/build/library.min.js
components/static/components/js/build/navigation.min.js
components/static/components/js/build/questions.min.js
components/static/components/js/build/rationales.min.js
components/static/components/js/build/search.min.js
components/static/components/js/build/styleguide.min.js
components/static/components/js/build/updateAssignment.min.js
components/static/components/js/build/updateProfile.min.js