Metadata-Version: 2.1
Name: SALTISE_components
Version: 0.2.15
Summary: A Django app to build and test a collection of front-end components for myDALITE
Author: Jonathon Sumner
Author-email: jsumner@dawsoncollege.qc.ca
License: LICENSE.txt
Classifier: Environment :: Web Environment
Classifier: Framework :: Django
Classifier: Framework :: Django :: 2.2
Classifier: Framework :: Django :: 3.2
Classifier: Intended Audience :: Developers
Classifier: License :: OSI Approved :: BSD License
Classifier: Operating System :: OS Independent
Classifier: Programming Language :: Python
Classifier: Programming Language :: Python :: 3
Classifier: Programming Language :: Python :: 3 :: Only
Classifier: Programming Language :: Python :: 3.9
Classifier: Topic :: Internet :: WWW/HTTP
Classifier: Topic :: Internet :: WWW/HTTP :: Dynamic Content
License-File: LICENSE
Requires-Dist: django<=3.3,>=2.2
